emaildeliverability/__init__.py
emaildeliverability/admin.py
emaildeliverability/apps.py
emaildeliverability/models.py
emaildeliverability/settings.py
emaildeliverability/tests.py
emaildeliverability/urls.py
emaildeliverability/views.py
emaildeliverability/migrations/__init__.py
django_emaildeliverability-0.3.5.dist-info/LICENSE
django_emaildeliverability-0.3.5.dist-info/METADATA
django_emaildeliverability-0.3.5.dist-info/WHEEL
django_emaildeliverability-0.3.5.dist-info/top_level.txt
django_emaildeliverability-0.3.5.dist-info/RECORD
