Metadata-Version: 2.1
Name: django-emaildeliverability
Version: 0.3.5
Summary: A Django app to ensure that emails reach their intended destination
Home-page: https://github.com/tamoeinnovation/django-emaildeliverability
Author: Tamoe Innovation
Author-email: info@tamoe.es
License: GPL-3.0
Classifier: Environment :: Web Environment
Classifier: Framework :: Django
Classifier: Intended Audience :: Developers
Classifier: License :: OSI Approved :: BSD License
Classifier: Operating System :: OS Independent
Classifier: Programming Language :: Python
Classifier: Programming Language :: Python :: 3
Classifier: Programming Language :: Python :: 3 :: Only
Classifier: Topic :: Internet :: WWW/HTTP
Classifier: Topic :: Internet :: WWW/HTTP :: Dynamic Content
Requires-Python: >=3.9
License-File: LICENSE
Requires-Dist: Django >=3.2
Requires-Dist: imap-tools ==1.4.0
Requires-Dist: loguru ==0.7.2
